importpy/__init__.py
importpy/protocol.py
importpy/protocol_impl.py
importpy-0.1.2.dist-info/licenses/LICENSE
importpy-0.1.2.dist-info/METADATA
importpy-0.1.2.dist-info/WHEEL
importpy-0.1.2.dist-info/top_level.txt
importpy-0.1.2.dist-info/RECORD
