Metadata-Version: 2.4
Name: importpy
Version: 0.1.2
Summary: Dynamic, lazy-style module importer for Python. 
Home-page: https://github.com/waveware4ai/importpy
Author: 14mhz
Author-email: 14mhz <14mhz@hanmail.net>
License: Apache-2.0
Project-URL: Home, https://github.com/waveware4ai/importpy
Project-URL: Source, https://github.com/waveware4ai/importpy
Keywords: import,package,dynamic,lazy,module
Classifier: Programming Language :: Python :: 3.8
Classifier: Programming Language :: Python :: 3 :: Only
Classifier: License :: OSI Approved :: MIT License
Classifier: Operating System :: OS Independent
Requires-Python: >=3.8
License-File: LICENSE
Provides-Extra: dev
Requires-Dist: pytest>=6.0; extra == "dev"
Requires-Dist: pytest-cov; extra == "dev"
Requires-Dist: flake8; extra == "dev"
Dynamic: author
Dynamic: home-page
Dynamic: license-file
Dynamic: requires-python
